ptbmodels/__init__.py
ptbmodels/models.py
ptbmodels-0.2.19.dist-info/WHEEL
ptbmodels-0.2.19.dist-info/METADATA
ptbmodels-0.2.19.dist-info/RECORD
