Metadata-Version: 2.1
Name: ptbmodels
Version: 0.2.19
Summary: SQLModel common code for Pop the Bubble
Author: Raaid
Author-email: raaid@protonmail.com
Requires-Python: >=3.9,<4.0
Classifier: Programming Language :: Python :: 3
Classifier: Programming Language :: Python :: 3.10
Classifier: Programming Language :: Python :: 3.9
Requires-Dist: pydantic (>=1.9.0,<2.0.0)
Requires-Dist: sqlmodel (>=0.0.4,<0.0.5)
